visgraph/__init__.py
visgraph/visgraph.py
visgraph-0.0.9.dist-info/METADATA
visgraph-0.0.9.dist-info/WHEEL
visgraph-0.0.9.dist-info/licenses/LICENSE.txt
visgraph-0.0.9.dist-info/RECORD
