Metadata-Version: 2.1
Name: visgraph
Version: 0.0.9
Summary: Visgraph API allows the user to interface with a visgraph session using python scripts.
License-File: LICENSE.txt
Keywords: computational,modeling,network,visualization
Classifier: Programming Language :: Python :: 3
Requires-Dist: importlib-metadata; python_version < '3.8'
Requires-Dist: requests
Requires-Dist: websockets
